{
  "generatedAt": "2026-03-30T13:48:31.777367+00:00",
  "latestDate": "2026-03-30",
  "lastUpdated": "2026-03-30T13:48:31.727071+00:00",
  "historyRows": 5407,
  "historyLightRows": 2911,
  "schemaVersion": "v3",
  "indicatorSet": "core6_bottom_v2",
  "thresholds": {
    "priceMa200wRatio": {
      "trigger": 1.0,
      "deep": 0.85
    },
    "priceRealizedRatio": {
      "trigger": 1.0,
      "deep": 0.9
    },
    "reserveRisk": {
      "trigger": 0.001637,
      "deep": 0.0012492
    },
    "sthSopr": {
      "trigger": 1.0,
      "deep": 0.97
    },
    "sthMvrv": {
      "trigger": 1.0,
      "deep": 0.85
    },
    "puellMultiple": {
      "trigger": 0.6,
      "deep": 0.5
    }
  }
}
